svsdatasetio/__init__.py
svsdatasetio/dataset.py
svsdatasetio/decoder.py
svsdatasetio/getlabels.py
svsdatasetio-1.0.0.dist-info/LICENSE
svsdatasetio-1.0.0.dist-info/METADATA
svsdatasetio-1.0.0.dist-info/WHEEL
svsdatasetio-1.0.0.dist-info/top_level.txt
svsdatasetio-1.0.0.dist-info/RECORD
