Metadata-Version: 2.1
Name: svsdatasetio
Version: 1.0.0
Summary: Singing Voice Synthesis Dataset Loader
Author: Li Lingyi
Author-email: alan_sudo@yeah.net
Maintainer: Project VsingerXiaoice Group
Maintainer-email: alan_sudo@yeah.net
License: This is free and unencumbered software released into the public domain.
Requires: textgrid
Requires: torch
Requires: torchaudio
License-File: LICENSE
